{
  "id": "569ef49e-673d-4815-897c-324d4ea17847",
  "prevId": "00000000-0000-0000-0000-000000000000",
  "version": "7",
  "dialect": "postgresql",
  "tables": {
    "public.access_logs": {
      "name": "access_logs",
      "schema": "",
      "columns": {
        "id": {
          "name": "id",
          "type": "uuid",
          "primaryKey": true,
          "notNull": true,
          "default": "gen_random_uuid()"
        },
        "user_id": {
          "name": "user_id",
          "type": "uuid",
          "primaryKey": false,
          "notNull": true
        },
        "file_id": {
          "name": "file_id",
          "type": "uuid",
          "primaryKey": false,
          "notNull": true
        },
        "action": {
          "name": "action",
          "type": "file_access_action",
          "typeSchema": "public",
          "primaryKey": false,
          "notNull": true
        },
        "ip_address": {
          "name": "ip_address",
          "type": "text",
          "primaryKey": false,
          "notNull": false
        },
        "signed_url_id": {
          "name": "signed_url_id",
          "type": "text",
          "primaryKey": false,
          "notNull": false
        },
        "created_at": {
          "name": "created_at",
          "type": "timestamp with time zone",
          "primaryKey": false,
          "notNull": true,
          "default": "now()"
        }
      },
      "indexes": {
        "access_logs_file_created_at_idx": {
          "name": "access_logs_file_created_at_idx",
          "columns": [
            {
              "expression": "file_id",
              "isExpression": false,
              "asc": true,
              "nulls": "last"
            },
            {
              "expression": "created_at",
              "isExpression": false,
              "asc": true,
              "nulls": "last"
            }
          ],
          "isUnique": false,
          "concurrently": false,
          "method": "btree",
          "with": {}
        }
      },
      "foreignKeys": {},
      "compositePrimaryKeys": {},
      "uniqueConstraints": {},
      "policies": {},
      "checkConstraints": {},
      "isRLSEnabled": false
    },
    "public.audit_logs": {
      "name": "audit_logs",
      "schema": "",
      "columns": {
        "id": {
          "name": "id",
          "type": "uuid",
          "primaryKey": true,
          "notNull": true,
          "default": "gen_random_uuid()"
        },
        "actor_user_id": {
          "name": "actor_user_id",
          "type": "uuid",
          "primaryKey": false,
          "notNull": false
        },
        "actor_role": {
          "name": "actor_role",
          "type": "text",
          "primaryKey": false,
          "notNull": false
        },
        "action": {
          "name": "action",
          "type": "text",
          "primaryKey": false,
          "notNull": true
        },
        "target_type": {
          "name": "target_type",
          "type": "text",
          "primaryKey": false,
          "notNull": false
        },
        "target_id": {
          "name": "target_id",
          "type": "uuid",
          "primaryKey": false,
          "notNull": false
        },
        "reason": {
          "name": "reason",
          "type": "text",
          "primaryKey": false,
          "notNull": false
        },
        "ip_address": {
          "name": "ip_address",
          "type": "text",
          "primaryKey": false,
          "notNull": false
        },
        "user_agent": {
          "name": "user_agent",
          "type": "text",
          "primaryKey": false,
          "notNull": false
        },
        "context": {
          "name": "context",
          "type": "jsonb",
          "primaryKey": false,
          "notNull": false
        },
        "created_at": {
          "name": "created_at",
          "type": "timestamp with time zone",
          "primaryKey": false,
          "notNull": true,
          "default": "now()"
        }
      },
      "indexes": {
        "audit_logs_actor_created_at_idx": {
          "name": "audit_logs_actor_created_at_idx",
          "columns": [
            {
              "expression": "actor_user_id",
              "isExpression": false,
              "asc": true,
              "nulls": "last"
            },
            {
              "expression": "created_at",
              "isExpression": false,
              "asc": true,
              "nulls": "last"
            }
          ],
          "isUnique": false,
          "concurrently": false,
          "method": "btree",
          "with": {}
        },
        "audit_logs_target_idx": {
          "name": "audit_logs_target_idx",
          "columns": [
            {
              "expression": "target_type",
              "isExpression": false,
              "asc": true,
              "nulls": "last"
            },
            {
              "expression": "target_id",
              "isExpression": false,
              "asc": true,
              "nulls": "last"
            }
          ],
          "isUnique": false,
          "concurrently": false,
          "method": "btree",
          "with": {}
        }
      },
      "foreignKeys": {},
      "compositePrimaryKeys": {},
      "uniqueConstraints": {},
      "policies": {},
      "checkConstraints": {},
      "isRLSEnabled": false
    },
    "public.availability_slots": {
      "name": "availability_slots",
      "schema": "",
      "columns": {
        "id": {
          "name": "id",
          "type": "uuid",
          "primaryKey": true,
          "notNull": true,
          "default": "gen_random_uuid()"
        },
        "supervisor_profile_id": {
          "name": "supervisor_profile_id",
          "type": "uuid",
          "primaryKey": false,
          "notNull": true
        },
        "weekday": {
          "name": "weekday",
          "type": "smallint",
          "primaryKey": false,
          "notNull": false
        },
        "start_time": {
          "name": "start_time",
          "type": "time",
          "primaryKey": false,
          "notNull": false
        },
        "end_time": {
          "name": "end_time",
          "type": "time",
          "primaryKey": false,
          "notNull": false
        },
        "timezone": {
          "name": "timezone",
          "type": "text",
          "primaryKey": false,
          "notNull": true,
          "default": "'Asia/Seoul'"
        }
      },
      "indexes": {},
      "foreignKeys": {
        "availability_slots_supervisor_profile_id_supervisor_profiles_id_fk": {
          "name": "availability_slots_supervisor_profile_id_supervisor_profiles_id_fk",
          "tableFrom": "availability_slots",
          "tableTo": "supervisor_profiles",
          "columnsFrom": ["supervisor_profile_id"],
          "columnsTo": ["id"],
          "onDelete": "no action",
          "onUpdate": "no action"
        }
      },
      "compositePrimaryKeys": {},
      "uniqueConstraints": {},
      "policies": {},
      "checkConstraints": {},
      "isRLSEnabled": false
    },
    "public.bookings": {
      "name": "bookings",
      "schema": "",
      "columns": {
        "id": {
          "name": "id",
          "type": "uuid",
          "primaryKey": true,
          "notNull": true,
          "default": "gen_random_uuid()"
        },
        "supervision_request_id": {
          "name": "supervision_request_id",
          "type": "uuid",
          "primaryKey": false,
          "notNull": true
        },
        "scheduled_start": {
          "name": "scheduled_start",
          "type": "timestamp with time zone",
          "primaryKey": false,
          "notNull": true
        },
        "scheduled_end": {
          "name": "scheduled_end",
          "type": "timestamp with time zone",
          "primaryKey": false,
          "notNull": true
        },
        "meeting_url_enc": {
          "name": "meeting_url_enc",
          "type": "bytea",
          "primaryKey": false,
          "notNull": false
        },
        "status": {
          "name": "status",
          "type": "booking_status",
          "typeSchema": "public",
          "primaryKey": false,
          "notNull": true,
          "default": "'scheduled'"
        },
        "created_at": {
          "name": "created_at",
          "type": "timestamp with time zone",
          "primaryKey": false,
          "notNull": true,
          "default": "now()"
        }
      },
      "indexes": {},
      "foreignKeys": {
        "bookings_supervision_request_id_supervision_requests_id_fk": {
          "name": "bookings_supervision_request_id_supervision_requests_id_fk",
          "tableFrom": "bookings",
          "tableTo": "supervision_requests",
          "columnsFrom": ["supervision_request_id"],
          "columnsTo": ["id"],
          "onDelete": "no action",
          "onUpdate": "no action"
        }
      },
      "compositePrimaryKeys": {},
      "uniqueConstraints": {},
      "policies": {},
      "checkConstraints": {},
      "isRLSEnabled": false
    },
    "public.case_files": {
      "name": "case_files",
      "schema": "",
      "columns": {
        "id": {
          "name": "id",
          "type": "uuid",
          "primaryKey": true,
          "notNull": true,
          "default": "gen_random_uuid()"
        },
        "case_packet_id": {
          "name": "case_packet_id",
          "type": "uuid",
          "primaryKey": false,
          "notNull": true
        },
        "uploaded_by": {
          "name": "uploaded_by",
          "type": "uuid",
          "primaryKey": false,
          "notNull": true
        },
        "kind": {
          "name": "kind",
          "type": "case_file_kind",
          "typeSchema": "public",
          "primaryKey": false,
          "notNull": true
        },
        "original_filename": {
          "name": "original_filename",
          "type": "text",
          "primaryKey": false,
          "notNull": true
        },
        "mime_type": {
          "name": "mime_type",
          "type": "text",
          "primaryKey": false,
          "notNull": true
        },
        "size_bytes": {
          "name": "size_bytes",
          "type": "integer",
          "primaryKey": false,
          "notNull": true
        },
        "storage_key": {
          "name": "storage_key",
          "type": "text",
          "primaryKey": false,
          "notNull": true
        },
        "kms_key_id": {
          "name": "kms_key_id",
          "type": "text",
          "primaryKey": false,
          "notNull": false
        },
        "checksum_sha256": {
          "name": "checksum_sha256",
          "type": "text",
          "primaryKey": false,
          "notNull": false
        },
        "virus_scan_status": {
          "name": "virus_scan_status",
          "type": "virus_scan_status",
          "typeSchema": "public",
          "primaryKey": false,
          "notNull": true,
          "default": "'pending'"
        },
        "phi_scan_status": {
          "name": "phi_scan_status",
          "type": "phi_scan_status",
          "typeSchema": "public",
          "primaryKey": false,
          "notNull": true,
          "default": "'pending'"
        },
        "uploaded_at": {
          "name": "uploaded_at",
          "type": "timestamp with time zone",
          "primaryKey": false,
          "notNull": true,
          "default": "now()"
        },
        "retention_expires_at": {
          "name": "retention_expires_at",
          "type": "timestamp with time zone",
          "primaryKey": false,
          "notNull": false
        },
        "deleted_at": {
          "name": "deleted_at",
          "type": "timestamp with time zone",
          "primaryKey": false,
          "notNull": false
        }
      },
      "indexes": {
        "case_files_case_packet_id_idx": {
          "name": "case_files_case_packet_id_idx",
          "columns": [
            {
              "expression": "case_packet_id",
              "isExpression": false,
              "asc": true,
              "nulls": "last"
            }
          ],
          "isUnique": false,
          "concurrently": false,
          "method": "btree",
          "with": {}
        },
        "case_files_retention_expires_at_idx": {
          "name": "case_files_retention_expires_at_idx",
          "columns": [
            {
              "expression": "retention_expires_at",
              "isExpression": false,
              "asc": true,
              "nulls": "last"
            }
          ],
          "isUnique": false,
          "concurrently": false,
          "method": "btree",
          "with": {}
        }
      },
      "foreignKeys": {
        "case_files_case_packet_id_case_packets_id_fk": {
          "name": "case_files_case_packet_id_case_packets_id_fk",
          "tableFrom": "case_files",
          "tableTo": "case_packets",
          "columnsFrom": ["case_packet_id"],
          "columnsTo": ["id"],
          "onDelete": "no action",
          "onUpdate": "no action"
        },
        "case_files_uploaded_by_users_id_fk": {
          "name": "case_files_uploaded_by_users_id_fk",
          "tableFrom": "case_files",
          "tableTo": "users",
          "columnsFrom": ["uploaded_by"],
          "columnsTo": ["id"],
          "onDelete": "no action",
          "onUpdate": "no action"
        }
      },
      "compositePrimaryKeys": {},
      "uniqueConstraints": {},
      "policies": {},
      "checkConstraints": {},
      "isRLSEnabled": false
    },
    "public.case_packets": {
      "name": "case_packets",
      "schema": "",
      "columns": {
        "id": {
          "name": "id",
          "type": "uuid",
          "primaryKey": true,
          "notNull": true,
          "default": "gen_random_uuid()"
        },
        "supervision_request_id": {
          "name": "supervision_request_id",
          "type": "uuid",
          "primaryKey": false,
          "notNull": true
        },
        "title_enc": {
          "name": "title_enc",
          "type": "bytea",
          "primaryKey": false,
          "notNull": true
        },
        "purpose": {
          "name": "purpose",
          "type": "jsonb",
          "primaryKey": false,
          "notNull": false
        },
        "client_age_band": {
          "name": "client_age_band",
          "type": "text",
          "primaryKey": false,
          "notNull": false
        },
        "client_gender": {
          "name": "client_gender",
          "type": "text",
          "primaryKey": false,
          "notNull": false
        },
        "setting": {
          "name": "setting",
          "type": "text",
          "primaryKey": false,
          "notNull": false
        },
        "chief_complaint_enc": {
          "name": "chief_complaint_enc",
          "type": "bytea",
          "primaryKey": false,
          "notNull": false
        },
        "referral_reason_enc": {
          "name": "referral_reason_enc",
          "type": "bytea",
          "primaryKey": false,
          "notNull": false
        },
        "tests_used": {
          "name": "tests_used",
          "type": "jsonb",
          "primaryKey": false,
          "notNull": false
        },
        "request_items": {
          "name": "request_items",
          "type": "jsonb",
          "primaryKey": false,
          "notNull": false
        },
        "preferred_method": {
          "name": "preferred_method",
          "type": "preferred_method",
          "typeSchema": "public",
          "primaryKey": false,
          "notNull": false
        },
        "needs_completion_record": {
          "name": "needs_completion_record",
          "type": "boolean",
          "primaryKey": false,
          "notNull": true,
          "default": true
        },
        "created_at": {
          "name": "created_at",
          "type": "timestamp with time zone",
          "primaryKey": false,
          "notNull": true,
          "default": "now()"
        }
      },
      "indexes": {},
      "foreignKeys": {
        "case_packets_supervision_request_id_supervision_requests_id_fk": {
          "name": "case_packets_supervision_request_id_supervision_requests_id_fk",
          "tableFrom": "case_packets",
          "tableTo": "supervision_requests",
          "columnsFrom": ["supervision_request_id"],
          "columnsTo": ["id"],
          "onDelete": "no action",
          "onUpdate": "no action"
        }
      },
      "compositePrimaryKeys": {},
      "uniqueConstraints": {},
      "policies": {},
      "checkConstraints": {},
      "isRLSEnabled": false
    },
    "public.completion_records": {
      "name": "completion_records",
      "schema": "",
      "columns": {
        "id": {
          "name": "id",
          "type": "uuid",
          "primaryKey": true,
          "notNull": true,
          "default": "gen_random_uuid()"
        },
        "supervision_request_id": {
          "name": "supervision_request_id",
          "type": "uuid",
          "primaryKey": false,
          "notNull": true
        },
        "record_no": {
          "name": "record_no",
          "type": "text",
          "primaryKey": false,
          "notNull": true
        },
        "supervisor_id": {
          "name": "supervisor_id",
          "type": "uuid",
          "primaryKey": false,
          "notNull": true
        },
        "supervisee_id": {
          "name": "supervisee_id",
          "type": "uuid",
          "primaryKey": false,
          "notNull": true
        },
        "supervisor_qualification_snapshot": {
          "name": "supervisor_qualification_snapshot",
          "type": "jsonb",
          "primaryKey": false,
          "notNull": false
        },
        "reviewed_materials": {
          "name": "reviewed_materials",
          "type": "jsonb",
          "primaryKey": false,
          "notNull": false
        },
        "scope": {
          "name": "scope",
          "type": "jsonb",
          "primaryKey": false,
          "notNull": false
        },
        "limitations_enc": {
          "name": "limitations_enc",
          "type": "bytea",
          "primaryKey": false,
          "notNull": false
        },
        "responsibility_notice": {
          "name": "responsibility_notice",
          "type": "text",
          "primaryKey": false,
          "notNull": false
        },
        "signature_storage_key": {
          "name": "signature_storage_key",
          "type": "text",
          "primaryKey": false,
          "notNull": false
        },
        "signature_attached_at": {
          "name": "signature_attached_at",
          "type": "timestamp with time zone",
          "primaryKey": false,
          "notNull": false
        },
        "issued_at": {
          "name": "issued_at",
          "type": "timestamp with time zone",
          "primaryKey": false,
          "notNull": true,
          "default": "now()"
        },
        "pdf_storage_key": {
          "name": "pdf_storage_key",
          "type": "text",
          "primaryKey": false,
          "notNull": false
        }
      },
      "indexes": {
        "completion_records_request_unique": {
          "name": "completion_records_request_unique",
          "columns": [
            {
              "expression": "supervision_request_id",
              "isExpression": false,
              "asc": true,
              "nulls": "last"
            }
          ],
          "isUnique": true,
          "concurrently": false,
          "method": "btree",
          "with": {}
        },
        "completion_records_record_no_unique": {
          "name": "completion_records_record_no_unique",
          "columns": [
            {
              "expression": "record_no",
              "isExpression": false,
              "asc": true,
              "nulls": "last"
            }
          ],
          "isUnique": true,
          "concurrently": false,
          "method": "btree",
          "with": {}
        }
      },
      "foreignKeys": {
        "completion_records_supervision_request_id_supervision_requests_id_fk": {
          "name": "completion_records_supervision_request_id_supervision_requests_id_fk",
          "tableFrom": "completion_records",
          "tableTo": "supervision_requests",
          "columnsFrom": ["supervision_request_id"],
          "columnsTo": ["id"],
          "onDelete": "no action",
          "onUpdate": "no action"
        },
        "completion_records_supervisor_id_users_id_fk": {
          "name": "completion_records_supervisor_id_users_id_fk",
          "tableFrom": "completion_records",
          "tableTo": "users",
          "columnsFrom": ["supervisor_id"],
          "columnsTo": ["id"],
          "onDelete": "no action",
          "onUpdate": "no action"
        },
        "completion_records_supervisee_id_users_id_fk": {
          "name": "completion_records_supervisee_id_users_id_fk",
          "tableFrom": "completion_records",
          "tableTo": "users",
          "columnsFrom": ["supervisee_id"],
          "columnsTo": ["id"],
          "onDelete": "no action",
          "onUpdate": "no action"
        }
      },
      "compositePrimaryKeys": {},
      "uniqueConstraints": {},
      "policies": {},
      "checkConstraints": {},
      "isRLSEnabled": false
    },
    "public.consent_records": {
      "name": "consent_records",
      "schema": "",
      "columns": {
        "id": {
          "name": "id",
          "type": "uuid",
          "primaryKey": true,
          "notNull": true,
          "default": "gen_random_uuid()"
        },
        "user_id": {
          "name": "user_id",
          "type": "uuid",
          "primaryKey": false,
          "notNull": true
        },
        "terms_version_id": {
          "name": "terms_version_id",
          "type": "uuid",
          "primaryKey": false,
          "notNull": true
        },
        "consent_type": {
          "name": "consent_type",
          "type": "consent_type",
          "typeSchema": "public",
          "primaryKey": false,
          "notNull": true
        },
        "consented": {
          "name": "consented",
          "type": "boolean",
          "primaryKey": false,
          "notNull": true
        },
        "consented_at": {
          "name": "consented_at",
          "type": "timestamp with time zone",
          "primaryKey": false,
          "notNull": true,
          "default": "now()"
        },
        "ip_address": {
          "name": "ip_address",
          "type": "text",
          "primaryKey": false,
          "notNull": false
        },
        "user_agent": {
          "name": "user_agent",
          "type": "text",
          "primaryKey": false,
          "notNull": false
        }
      },
      "indexes": {
        "consent_records_user_type_idx": {
          "name": "consent_records_user_type_idx",
          "columns": [
            {
              "expression": "user_id",
              "isExpression": false,
              "asc": true,
              "nulls": "last"
            },
            {
              "expression": "consent_type",
              "isExpression": false,
              "asc": true,
              "nulls": "last"
            }
          ],
          "isUnique": false,
          "concurrently": false,
          "method": "btree",
          "with": {}
        }
      },
      "foreignKeys": {
        "consent_records_user_id_users_id_fk": {
          "name": "consent_records_user_id_users_id_fk",
          "tableFrom": "consent_records",
          "tableTo": "users",
          "columnsFrom": ["user_id"],
          "columnsTo": ["id"],
          "onDelete": "no action",
          "onUpdate": "no action"
        },
        "consent_records_terms_version_id_terms_versions_id_fk": {
          "name": "consent_records_terms_version_id_terms_versions_id_fk",
          "tableFrom": "consent_records",
          "tableTo": "terms_versions",
          "columnsFrom": ["terms_version_id"],
          "columnsTo": ["id"],
          "onDelete": "no action",
          "onUpdate": "no action"
        }
      },
      "compositePrimaryKeys": {},
      "uniqueConstraints": {},
      "policies": {},
      "checkConstraints": {},
      "isRLSEnabled": false
    },
    "public.deidentification_checklists": {
      "name": "deidentification_checklists",
      "schema": "",
      "columns": {
        "id": {
          "name": "id",
          "type": "uuid",
          "primaryKey": true,
          "notNull": true,
          "default": "gen_random_uuid()"
        },
        "case_packet_id": {
          "name": "case_packet_id",
          "type": "uuid",
          "primaryKey": false,
          "notNull": true
        },
        "removed_name": {
          "name": "removed_name",
          "type": "boolean",
          "primaryKey": false,
          "notNull": true
        },
        "removed_rrn": {
          "name": "removed_rrn",
          "type": "boolean",
          "primaryKey": false,
          "notNull": true
        },
        "removed_phone": {
          "name": "removed_phone",
          "type": "boolean",
          "primaryKey": false,
          "notNull": true
        },
        "removed_address": {
          "name": "removed_address",
          "type": "boolean",
          "primaryKey": false,
          "notNull": true
        },
        "removed_guardian_name": {
          "name": "removed_guardian_name",
          "type": "boolean",
          "primaryKey": false,
          "notNull": true
        },
        "removed_org_name": {
          "name": "removed_org_name",
          "type": "boolean",
          "primaryKey": false,
          "notNull": true
        },
        "removed_chart_number": {
          "name": "removed_chart_number",
          "type": "boolean",
          "primaryKey": false,
          "notNull": true
        },
        "filename_safe": {
          "name": "filename_safe",
          "type": "boolean",
          "primaryKey": false,
          "notNull": true
        },
        "raw_data_safe": {
          "name": "raw_data_safe",
          "type": "boolean",
          "primaryKey": false,
          "notNull": true
        },
        "minimal_info": {
          "name": "minimal_info",
          "type": "boolean",
          "primaryKey": false,
          "notNull": true
        },
        "client_consent_confirmed": {
          "name": "client_consent_confirmed",
          "type": "boolean",
          "primaryKey": false,
          "notNull": true
        },
        "purpose_understood": {
          "name": "purpose_understood",
          "type": "boolean",
          "primaryKey": false,
          "notNull": true
        },
        "acknowledged_at": {
          "name": "acknowledged_at",
          "type": "timestamp with time zone",
          "primaryKey": false,
          "notNull": true,
          "default": "now()"
        },
        "acknowledged_by": {
          "name": "acknowledged_by",
          "type": "uuid",
          "primaryKey": false,
          "notNull": false
        }
      },
      "indexes": {
        "deidentification_checklists_case_packet_unique": {
          "name": "deidentification_checklists_case_packet_unique",
          "columns": [
            {
              "expression": "case_packet_id",
              "isExpression": false,
              "asc": true,
              "nulls": "last"
            }
          ],
          "isUnique": true,
          "concurrently": false,
          "method": "btree",
          "with": {}
        }
      },
      "foreignKeys": {
        "deidentification_checklists_case_packet_id_case_packets_id_fk": {
          "name": "deidentification_checklists_case_packet_id_case_packets_id_fk",
          "tableFrom": "deidentification_checklists",
          "tableTo": "case_packets",
          "columnsFrom": ["case_packet_id"],
          "columnsTo": ["id"],
          "onDelete": "no action",
          "onUpdate": "no action"
        },
        "deidentification_checklists_acknowledged_by_users_id_fk": {
          "name": "deidentification_checklists_acknowledged_by_users_id_fk",
          "tableFrom": "deidentification_checklists",
          "tableTo": "users",
          "columnsFrom": ["acknowledged_by"],
          "columnsTo": ["id"],
          "onDelete": "no action",
          "onUpdate": "no action"
        }
      },
      "compositePrimaryKeys": {},
      "uniqueConstraints": {},
      "policies": {},
      "checkConstraints": {},
      "isRLSEnabled": false
    },
    "public.deletion_requests": {
      "name": "deletion_requests",
      "schema": "",
      "columns": {
        "id": {
          "name": "id",
          "type": "uuid",
          "primaryKey": true,
          "notNull": true,
          "default": "gen_random_uuid()"
        },
        "requested_by": {
          "name": "requested_by",
          "type": "uuid",
          "primaryKey": false,
          "notNull": false
        },
        "target_type": {
          "name": "target_type",
          "type": "deletion_target_type",
          "typeSchema": "public",
          "primaryKey": false,
          "notNull": false
        },
        "target_id": {
          "name": "target_id",
          "type": "uuid",
          "primaryKey": false,
          "notNull": false
        },
        "reason": {
          "name": "reason",
          "type": "text",
          "primaryKey": false,
          "notNull": false
        },
        "status": {
          "name": "status",
          "type": "deletion_status",
          "typeSchema": "public",
          "primaryKey": false,
          "notNull": true,
          "default": "'pending'"
        },
        "processed_by": {
          "name": "processed_by",
          "type": "uuid",
          "primaryKey": false,
          "notNull": false
        },
        "processed_at": {
          "name": "processed_at",
          "type": "timestamp with time zone",
          "primaryKey": false,
          "notNull": false
        },
        "created_at": {
          "name": "created_at",
          "type": "timestamp with time zone",
          "primaryKey": false,
          "notNull": true,
          "default": "now()"
        }
      },
      "indexes": {},
      "foreignKeys": {},
      "compositePrimaryKeys": {},
      "uniqueConstraints": {},
      "policies": {},
      "checkConstraints": {},
      "isRLSEnabled": false
    },
    "public.disputes": {
      "name": "disputes",
      "schema": "",
      "columns": {
        "id": {
          "name": "id",
          "type": "uuid",
          "primaryKey": true,
          "notNull": true,
          "default": "gen_random_uuid()"
        },
        "supervision_request_id": {
          "name": "supervision_request_id",
          "type": "uuid",
          "primaryKey": false,
          "notNull": true
        },
        "raised_by": {
          "name": "raised_by",
          "type": "uuid",
          "primaryKey": false,
          "notNull": true
        },
        "reason": {
          "name": "reason",
          "type": "text",
          "primaryKey": false,
          "notNull": false
        },
        "description_enc": {
          "name": "description_enc",
          "type": "bytea",
          "primaryKey": false,
          "notNull": false
        },
        "status": {
          "name": "status",
          "type": "dispute_status",
          "typeSchema": "public",
          "primaryKey": false,
          "notNull": true,
          "default": "'open'"
        },
        "resolution_note": {
          "name": "resolution_note",
          "type": "text",
          "primaryKey": false,
          "notNull": false
        },
        "resolved_by": {
          "name": "resolved_by",
          "type": "uuid",
          "primaryKey": false,
          "notNull": false
        },
        "resolved_at": {
          "name": "resolved_at",
          "type": "timestamp with time zone",
          "primaryKey": false,
          "notNull": false
        },
        "created_at": {
          "name": "created_at",
          "type": "timestamp with time zone",
          "primaryKey": false,
          "notNull": true,
          "default": "now()"
        }
      },
      "indexes": {},
      "foreignKeys": {
        "disputes_supervision_request_id_supervision_requests_id_fk": {
          "name": "disputes_supervision_request_id_supervision_requests_id_fk",
          "tableFrom": "disputes",
          "tableTo": "supervision_requests",
          "columnsFrom": ["supervision_request_id"],
          "columnsTo": ["id"],
          "onDelete": "no action",
          "onUpdate": "no action"
        },
        "disputes_raised_by_users_id_fk": {
          "name": "disputes_raised_by_users_id_fk",
          "tableFrom": "disputes",
          "tableTo": "users",
          "columnsFrom": ["raised_by"],
          "columnsTo": ["id"],
          "onDelete": "no action",
          "onUpdate": "no action"
        },
        "disputes_resolved_by_users_id_fk": {
          "name": "disputes_resolved_by_users_id_fk",
          "tableFrom": "disputes",
          "tableTo": "users",
          "columnsFrom": ["resolved_by"],
          "columnsTo": ["id"],
          "onDelete": "no action",
          "onUpdate": "no action"
        }
      },
      "compositePrimaryKeys": {},
      "uniqueConstraints": {},
      "policies": {},
      "checkConstraints": {},
      "isRLSEnabled": false
    },
    "public.feedbacks": {
      "name": "feedbacks",
      "schema": "",
      "columns": {
        "id": {
          "name": "id",
          "type": "uuid",
          "primaryKey": true,
          "notNull": true,
          "default": "gen_random_uuid()"
        },
        "supervision_request_id": {
          "name": "supervision_request_id",
          "type": "uuid",
          "primaryKey": false,
          "notNull": true
        },
        "supervisor_id": {
          "name": "supervisor_id",
          "type": "uuid",
          "primaryKey": false,
          "notNull": true
        },
        "summary_enc": {
          "name": "summary_enc",
          "type": "bytea",
          "primaryKey": false,
          "notNull": false
        },
        "recommendations_enc": {
          "name": "recommendations_enc",
          "type": "bytea",
          "primaryKey": false,
          "notNull": false
        },
        "submitted_at": {
          "name": "submitted_at",
          "type": "timestamp with time zone",
          "primaryKey": false,
          "notNull": false
        }
      },
      "indexes": {},
      "foreignKeys": {
        "feedbacks_supervision_request_id_supervision_requests_id_fk": {
          "name": "feedbacks_supervision_request_id_supervision_requests_id_fk",
          "tableFrom": "feedbacks",
          "tableTo": "supervision_requests",
          "columnsFrom": ["supervision_request_id"],
          "columnsTo": ["id"],
          "onDelete": "no action",
          "onUpdate": "no action"
        },
        "feedbacks_supervisor_id_users_id_fk": {
          "name": "feedbacks_supervisor_id_users_id_fk",
          "tableFrom": "feedbacks",
          "tableTo": "users",
          "columnsFrom": ["supervisor_id"],
          "columnsTo": ["id"],
          "onDelete": "no action",
          "onUpdate": "no action"
        }
      },
      "compositePrimaryKeys": {},
      "uniqueConstraints": {},
      "policies": {},
      "checkConstraints": {},
      "isRLSEnabled": false
    },
    "public.inline_comments": {
      "name": "inline_comments",
      "schema": "",
      "columns": {
        "id": {
          "name": "id",
          "type": "uuid",
          "primaryKey": true,
          "notNull": true,
          "default": "gen_random_uuid()"
        },
        "feedback_id": {
          "name": "feedback_id",
          "type": "uuid",
          "primaryKey": false,
          "notNull": true
        },
        "target_file_id": {
          "name": "target_file_id",
          "type": "uuid",
          "primaryKey": false,
          "notNull": false
        },
        "anchor": {
          "name": "anchor",
          "type": "jsonb",
          "primaryKey": false,
          "notNull": false
        },
        "comment_enc": {
          "name": "comment_enc",
          "type": "bytea",
          "primaryKey": false,
          "notNull": false
        },
        "severity": {
          "name": "severity",
          "type": "comment_severity",
          "typeSchema": "public",
          "primaryKey": false,
          "notNull": false
        },
        "created_at": {
          "name": "created_at",
          "type": "timestamp with time zone",
          "primaryKey": false,
          "notNull": true,
          "default": "now()"
        }
      },
      "indexes": {},
      "foreignKeys": {
        "inline_comments_feedback_id_feedbacks_id_fk": {
          "name": "inline_comments_feedback_id_feedbacks_id_fk",
          "tableFrom": "inline_comments",
          "tableTo": "feedbacks",
          "columnsFrom": ["feedback_id"],
          "columnsTo": ["id"],
          "onDelete": "no action",
          "onUpdate": "no action"
        },
        "inline_comments_target_file_id_case_files_id_fk": {
          "name": "inline_comments_target_file_id_case_files_id_fk",
          "tableFrom": "inline_comments",
          "tableTo": "case_files",
          "columnsFrom": ["target_file_id"],
          "columnsTo": ["id"],
          "onDelete": "no action",
          "onUpdate": "no action"
        }
      },
      "compositePrimaryKeys": {},
      "uniqueConstraints": {},
      "policies": {},
      "checkConstraints": {},
      "isRLSEnabled": false
    },
    "public.notifications": {
      "name": "notifications",
      "schema": "",
      "columns": {
        "id": {
          "name": "id",
          "type": "uuid",
          "primaryKey": true,
          "notNull": true,
          "default": "gen_random_uuid()"
        },
        "user_id": {
          "name": "user_id",
          "type": "uuid",
          "primaryKey": false,
          "notNull": true
        },
        "kind": {
          "name": "kind",
          "type": "text",
          "primaryKey": false,
          "notNull": true
        },
        "payload": {
          "name": "payload",
          "type": "jsonb",
          "primaryKey": false,
          "notNull": true
        },
        "read_at": {
          "name": "read_at",
          "type": "timestamp with time zone",
          "primaryKey": false,
          "notNull": false
        },
        "created_at": {
          "name": "created_at",
          "type": "timestamp with time zone",
          "primaryKey": false,
          "notNull": true,
          "default": "now()"
        }
      },
      "indexes": {
        "notifications_user_created_idx": {
          "name": "notifications_user_created_idx",
          "columns": [
            {
              "expression": "user_id",
              "isExpression": false,
              "asc": true,
              "nulls": "last"
            },
            {
              "expression": "created_at",
              "isExpression": false,
              "asc": true,
              "nulls": "last"
            }
          ],
          "isUnique": false,
          "concurrently": false,
          "method": "btree",
          "with": {}
        }
      },
      "foreignKeys": {
        "notifications_user_id_users_id_fk": {
          "name": "notifications_user_id_users_id_fk",
          "tableFrom": "notifications",
          "tableTo": "users",
          "columnsFrom": ["user_id"],
          "columnsTo": ["id"],
          "onDelete": "no action",
          "onUpdate": "no action"
        }
      },
      "compositePrimaryKeys": {},
      "uniqueConstraints": {},
      "policies": {},
      "checkConstraints": {},
      "isRLSEnabled": false
    },
    "public.payments": {
      "name": "payments",
      "schema": "",
      "columns": {
        "id": {
          "name": "id",
          "type": "uuid",
          "primaryKey": true,
          "notNull": true,
          "default": "gen_random_uuid()"
        },
        "supervision_request_id": {
          "name": "supervision_request_id",
          "type": "uuid",
          "primaryKey": false,
          "notNull": true
        },
        "amount_krw": {
          "name": "amount_krw",
          "type": "integer",
          "primaryKey": false,
          "notNull": true
        },
        "platform_fee_krw": {
          "name": "platform_fee_krw",
          "type": "integer",
          "primaryKey": false,
          "notNull": true
        },
        "supervisor_net_krw": {
          "name": "supervisor_net_krw",
          "type": "integer",
          "primaryKey": false,
          "notNull": true
        },
        "pg_provider": {
          "name": "pg_provider",
          "type": "text",
          "primaryKey": false,
          "notNull": true,
          "default": "'toss'"
        },
        "pg_payment_key": {
          "name": "pg_payment_key",
          "type": "text",
          "primaryKey": false,
          "notNull": false
        },
        "pg_order_id": {
          "name": "pg_order_id",
          "type": "text",
          "primaryKey": false,
          "notNull": true
        },
        "status": {
          "name": "status",
          "type": "payment_status",
          "typeSchema": "public",
          "primaryKey": false,
          "notNull": true,
          "default": "'pending'"
        },
        "paid_at": {
          "name": "paid_at",
          "type": "timestamp with time zone",
          "primaryKey": false,
          "notNull": false
        },
        "created_at": {
          "name": "created_at",
          "type": "timestamp with time zone",
          "primaryKey": false,
          "notNull": true,
          "default": "now()"
        }
      },
      "indexes": {
        "payments_supervision_request_status_idx": {
          "name": "payments_supervision_request_status_idx",
          "columns": [
            {
              "expression": "supervision_request_id",
              "isExpression": false,
              "asc": true,
              "nulls": "last"
            },
            {
              "expression": "status",
              "isExpression": false,
              "asc": true,
              "nulls": "last"
            }
          ],
          "isUnique": false,
          "concurrently": false,
          "method": "btree",
          "with": {}
        }
      },
      "foreignKeys": {
        "payments_supervision_request_id_supervision_requests_id_fk": {
          "name": "payments_supervision_request_id_supervision_requests_id_fk",
          "tableFrom": "payments",
          "tableTo": "supervision_requests",
          "columnsFrom": ["supervision_request_id"],
          "columnsTo": ["id"],
          "onDelete": "no action",
          "onUpdate": "no action"
        }
      },
      "compositePrimaryKeys": {},
      "uniqueConstraints": {},
      "policies": {},
      "checkConstraints": {},
      "isRLSEnabled": false
    },
    "public.payouts": {
      "name": "payouts",
      "schema": "",
      "columns": {
        "id": {
          "name": "id",
          "type": "uuid",
          "primaryKey": true,
          "notNull": true,
          "default": "gen_random_uuid()"
        },
        "supervisor_id": {
          "name": "supervisor_id",
          "type": "uuid",
          "primaryKey": false,
          "notNull": true
        },
        "period_start": {
          "name": "period_start",
          "type": "date",
          "primaryKey": false,
          "notNull": false
        },
        "period_end": {
          "name": "period_end",
          "type": "date",
          "primaryKey": false,
          "notNull": false
        },
        "gross_krw": {
          "name": "gross_krw",
          "type": "integer",
          "primaryKey": false,
          "notNull": false
        },
        "platform_fee_krw": {
          "name": "platform_fee_krw",
          "type": "integer",
          "primaryKey": false,
          "notNull": false
        },
        "net_krw": {
          "name": "net_krw",
          "type": "integer",
          "primaryKey": false,
          "notNull": false
        },
        "status": {
          "name": "status",
          "type": "payout_status",
          "typeSchema": "public",
          "primaryKey": false,
          "notNull": false
        },
        "scheduled_at": {
          "name": "scheduled_at",
          "type": "date",
          "primaryKey": false,
          "notNull": false
        },
        "paid_at": {
          "name": "paid_at",
          "type": "timestamp with time zone",
          "primaryKey": false,
          "notNull": false
        }
      },
      "indexes": {},
      "foreignKeys": {
        "payouts_supervisor_id_users_id_fk": {
          "name": "payouts_supervisor_id_users_id_fk",
          "tableFrom": "payouts",
          "tableTo": "users",
          "columnsFrom": ["supervisor_id"],
          "columnsTo": ["id"],
          "onDelete": "no action",
          "onUpdate": "no action"
        }
      },
      "compositePrimaryKeys": {},
      "uniqueConstraints": {},
      "policies": {},
      "checkConstraints": {},
      "isRLSEnabled": false
    },
    "public.qualifications": {
      "name": "qualifications",
      "schema": "",
      "columns": {
        "id": {
          "name": "id",
          "type": "uuid",
          "primaryKey": true,
          "notNull": true,
          "default": "gen_random_uuid()"
        },
        "supervisor_profile_id": {
          "name": "supervisor_profile_id",
          "type": "uuid",
          "primaryKey": false,
          "notNull": true
        },
        "name": {
          "name": "name",
          "type": "text",
          "primaryKey": false,
          "notNull": true
        },
        "number_enc": {
          "name": "number_enc",
          "type": "bytea",
          "primaryKey": false,
          "notNull": false
        },
        "issuing_body": {
          "name": "issuing_body",
          "type": "text",
          "primaryKey": false,
          "notNull": false
        },
        "issued_at": {
          "name": "issued_at",
          "type": "date",
          "primaryKey": false,
          "notNull": false
        },
        "expires_at": {
          "name": "expires_at",
          "type": "date",
          "primaryKey": false,
          "notNull": false
        },
        "evidence_file_id": {
          "name": "evidence_file_id",
          "type": "uuid",
          "primaryKey": false,
          "notNull": false
        },
        "verification_note": {
          "name": "verification_note",
          "type": "text",
          "primaryKey": false,
          "notNull": false
        },
        "status": {
          "name": "status",
          "type": "qualification_status",
          "typeSchema": "public",
          "primaryKey": false,
          "notNull": true,
          "default": "'pending'"
        },
        "created_at": {
          "name": "created_at",
          "type": "timestamp with time zone",
          "primaryKey": false,
          "notNull": true,
          "default": "now()"
        }
      },
      "indexes": {
        "qualifications_supervisor_profile_status_idx": {
          "name": "qualifications_supervisor_profile_status_idx",
          "columns": [
            {
              "expression": "supervisor_profile_id",
              "isExpression": false,
              "asc": true,
              "nulls": "last"
            },
            {
              "expression": "status",
              "isExpression": false,
              "asc": true,
              "nulls": "last"
            }
          ],
          "isUnique": false,
          "concurrently": false,
          "method": "btree",
          "with": {}
        }
      },
      "foreignKeys": {
        "qualifications_supervisor_profile_id_supervisor_profiles_id_fk": {
          "name": "qualifications_supervisor_profile_id_supervisor_profiles_id_fk",
          "tableFrom": "qualifications",
          "tableTo": "supervisor_profiles",
          "columnsFrom": ["supervisor_profile_id"],
          "columnsTo": ["id"],
          "onDelete": "no action",
          "onUpdate": "no action"
        }
      },
      "compositePrimaryKeys": {},
      "uniqueConstraints": {},
      "policies": {},
      "checkConstraints": {},
      "isRLSEnabled": false
    },
    "public.refunds": {
      "name": "refunds",
      "schema": "",
      "columns": {
        "id": {
          "name": "id",
          "type": "uuid",
          "primaryKey": true,
          "notNull": true,
          "default": "gen_random_uuid()"
        },
        "payment_id": {
          "name": "payment_id",
          "type": "uuid",
          "primaryKey": false,
          "notNull": true
        },
        "amount_krw": {
          "name": "amount_krw",
          "type": "integer",
          "primaryKey": false,
          "notNull": true
        },
        "reason": {
          "name": "reason",
          "type": "text",
          "primaryKey": false,
          "notNull": false
        },
        "initiated_by": {
          "name": "initiated_by",
          "type": "uuid",
          "primaryKey": false,
          "notNull": false
        },
        "status": {
          "name": "status",
          "type": "refund_status",
          "typeSchema": "public",
          "primaryKey": false,
          "notNull": true,
          "default": "'requested'"
        },
        "completed_at": {
          "name": "completed_at",
          "type": "timestamp with time zone",
          "primaryKey": false,
          "notNull": false
        },
        "created_at": {
          "name": "created_at",
          "type": "timestamp with time zone",
          "primaryKey": false,
          "notNull": true,
          "default": "now()"
        }
      },
      "indexes": {},
      "foreignKeys": {
        "refunds_payment_id_payments_id_fk": {
          "name": "refunds_payment_id_payments_id_fk",
          "tableFrom": "refunds",
          "tableTo": "payments",
          "columnsFrom": ["payment_id"],
          "columnsTo": ["id"],
          "onDelete": "no action",
          "onUpdate": "no action"
        },
        "refunds_initiated_by_users_id_fk": {
          "name": "refunds_initiated_by_users_id_fk",
          "tableFrom": "refunds",
          "tableTo": "users",
          "columnsFrom": ["initiated_by"],
          "columnsTo": ["id"],
          "onDelete": "no action",
          "onUpdate": "no action"
        }
      },
      "compositePrimaryKeys": {},
      "uniqueConstraints": {},
      "policies": {},
      "checkConstraints": {},
      "isRLSEnabled": false
    },
    "public.reports": {
      "name": "reports",
      "schema": "",
      "columns": {
        "id": {
          "name": "id",
          "type": "uuid",
          "primaryKey": true,
          "notNull": true,
          "default": "gen_random_uuid()"
        },
        "reporter_id": {
          "name": "reporter_id",
          "type": "uuid",
          "primaryKey": false,
          "notNull": false
        },
        "target_type": {
          "name": "target_type",
          "type": "text",
          "primaryKey": false,
          "notNull": false
        },
        "target_id": {
          "name": "target_id",
          "type": "uuid",
          "primaryKey": false,
          "notNull": false
        },
        "reason": {
          "name": "reason",
          "type": "text",
          "primaryKey": false,
          "notNull": false
        },
        "description": {
          "name": "description",
          "type": "text",
          "primaryKey": false,
          "notNull": false
        },
        "status": {
          "name": "status",
          "type": "report_status",
          "typeSchema": "public",
          "primaryKey": false,
          "notNull": true,
          "default": "'open'"
        },
        "created_at": {
          "name": "created_at",
          "type": "timestamp with time zone",
          "primaryKey": false,
          "notNull": true,
          "default": "now()"
        }
      },
      "indexes": {},
      "foreignKeys": {},
      "compositePrimaryKeys": {},
      "uniqueConstraints": {},
      "policies": {},
      "checkConstraints": {},
      "isRLSEnabled": false
    },
    "public.reviews": {
      "name": "reviews",
      "schema": "",
      "columns": {
        "id": {
          "name": "id",
          "type": "uuid",
          "primaryKey": true,
          "notNull": true,
          "default": "gen_random_uuid()"
        },
        "supervision_request_id": {
          "name": "supervision_request_id",
          "type": "uuid",
          "primaryKey": false,
          "notNull": true
        },
        "supervisor_id": {
          "name": "supervisor_id",
          "type": "uuid",
          "primaryKey": false,
          "notNull": true
        },
        "supervisee_id": {
          "name": "supervisee_id",
          "type": "uuid",
          "primaryKey": false,
          "notNull": true
        },
        "expertise": {
          "name": "expertise",
          "type": "smallint",
          "primaryKey": false,
          "notNull": false
        },
        "specificity": {
          "name": "specificity",
          "type": "smallint",
          "primaryKey": false,
          "notNull": false
        },
        "helpfulness": {
          "name": "helpfulness",
          "type": "smallint",
          "primaryKey": false,
          "notNull": false
        },
        "ethics": {
          "name": "ethics",
          "type": "smallint",
          "primaryKey": false,
          "notNull": false
        },
        "response_speed": {
          "name": "response_speed",
          "type": "smallint",
          "primaryKey": false,
          "notNull": false
        },
        "on_time": {
          "name": "on_time",
          "type": "smallint",
          "primaryKey": false,
          "notNull": false
        },
        "educational": {
          "name": "educational",
          "type": "smallint",
          "primaryKey": false,
          "notNull": false
        },
        "reuse_intent": {
          "name": "reuse_intent",
          "type": "smallint",
          "primaryKey": false,
          "notNull": false
        },
        "free_text": {
          "name": "free_text",
          "type": "text",
          "primaryKey": false,
          "notNull": false
        },
        "status": {
          "name": "status",
          "type": "review_status",
          "typeSchema": "public",
          "primaryKey": false,
          "notNull": true,
          "default": "'visible'"
        },
        "created_at": {
          "name": "created_at",
          "type": "timestamp with time zone",
          "primaryKey": false,
          "notNull": true,
          "default": "now()"
        }
      },
      "indexes": {
        "reviews_supervision_request_unique": {
          "name": "reviews_supervision_request_unique",
          "columns": [
            {
              "expression": "supervision_request_id",
              "isExpression": false,
              "asc": true,
              "nulls": "last"
            }
          ],
          "isUnique": true,
          "concurrently": false,
          "method": "btree",
          "with": {}
        }
      },
      "foreignKeys": {
        "reviews_supervision_request_id_supervision_requests_id_fk": {
          "name": "reviews_supervision_request_id_supervision_requests_id_fk",
          "tableFrom": "reviews",
          "tableTo": "supervision_requests",
          "columnsFrom": ["supervision_request_id"],
          "columnsTo": ["id"],
          "onDelete": "no action",
          "onUpdate": "no action"
        },
        "reviews_supervisor_id_users_id_fk": {
          "name": "reviews_supervisor_id_users_id_fk",
          "tableFrom": "reviews",
          "tableTo": "users",
          "columnsFrom": ["supervisor_id"],
          "columnsTo": ["id"],
          "onDelete": "no action",
          "onUpdate": "no action"
        },
        "reviews_supervisee_id_users_id_fk": {
          "name": "reviews_supervisee_id_users_id_fk",
          "tableFrom": "reviews",
          "tableTo": "users",
          "columnsFrom": ["supervisee_id"],
          "columnsTo": ["id"],
          "onDelete": "no action",
          "onUpdate": "no action"
        }
      },
      "compositePrimaryKeys": {},
      "uniqueConstraints": {},
      "policies": {},
      "checkConstraints": {},
      "isRLSEnabled": false
    },
    "public.service_products": {
      "name": "service_products",
      "schema": "",
      "columns": {
        "id": {
          "name": "id",
          "type": "uuid",
          "primaryKey": true,
          "notNull": true,
          "default": "gen_random_uuid()"
        },
        "supervisor_profile_id": {
          "name": "supervisor_profile_id",
          "type": "uuid",
          "primaryKey": false,
          "notNull": true
        },
        "kind": {
          "name": "kind",
          "type": "service_product_kind",
          "typeSchema": "public",
          "primaryKey": false,
          "notNull": true
        },
        "title": {
          "name": "title",
          "type": "text",
          "primaryKey": false,
          "notNull": true
        },
        "description": {
          "name": "description",
          "type": "text",
          "primaryKey": false,
          "notNull": false
        },
        "price_krw": {
          "name": "price_krw",
          "type": "integer",
          "primaryKey": false,
          "notNull": true
        },
        "turnaround_hours": {
          "name": "turnaround_hours",
          "type": "integer",
          "primaryKey": false,
          "notNull": false
        },
        "active": {
          "name": "active",
          "type": "boolean",
          "primaryKey": false,
          "notNull": true,
          "default": true
        },
        "created_at": {
          "name": "created_at",
          "type": "timestamp with time zone",
          "primaryKey": false,
          "notNull": true,
          "default": "now()"
        }
      },
      "indexes": {
        "service_products_supervisor_active_idx": {
          "name": "service_products_supervisor_active_idx",
          "columns": [
            {
              "expression": "supervisor_profile_id",
              "isExpression": false,
              "asc": true,
              "nulls": "last"
            },
            {
              "expression": "active",
              "isExpression": false,
              "asc": true,
              "nulls": "last"
            }
          ],
          "isUnique": false,
          "concurrently": false,
          "method": "btree",
          "with": {}
        }
      },
      "foreignKeys": {
        "service_products_supervisor_profile_id_supervisor_profiles_id_fk": {
          "name": "service_products_supervisor_profile_id_supervisor_profiles_id_fk",
          "tableFrom": "service_products",
          "tableTo": "supervisor_profiles",
          "columnsFrom": ["supervisor_profile_id"],
          "columnsTo": ["id"],
          "onDelete": "no action",
          "onUpdate": "no action"
        }
      },
      "compositePrimaryKeys": {},
      "uniqueConstraints": {},
      "policies": {},
      "checkConstraints": {},
      "isRLSEnabled": false
    },
    "public.specialty_catalog": {
      "name": "specialty_catalog",
      "schema": "",
      "columns": {
        "id": {
          "name": "id",
          "type": "uuid",
          "primaryKey": true,
          "notNull": true,
          "default": "gen_random_uuid()"
        },
        "code": {
          "name": "code",
          "type": "text",
          "primaryKey": false,
          "notNull": true
        },
        "label_ko": {
          "name": "label_ko",
          "type": "text",
          "primaryKey": false,
          "notNull": true
        },
        "parent_id": {
          "name": "parent_id",
          "type": "uuid",
          "primaryKey": false,
          "notNull": false
        },
        "display_order": {
          "name": "display_order",
          "type": "integer",
          "primaryKey": false,
          "notNull": false
        },
        "active": {
          "name": "active",
          "type": "boolean",
          "primaryKey": false,
          "notNull": true,
          "default": true
        }
      },
      "indexes": {
        "specialty_catalog_code_unique": {
          "name": "specialty_catalog_code_unique",
          "columns": [
            {
              "expression": "code",
              "isExpression": false,
              "asc": true,
              "nulls": "last"
            }
          ],
          "isUnique": true,
          "concurrently": false,
          "method": "btree",
          "with": {}
        }
      },
      "foreignKeys": {
        "specialty_catalog_parent_id_specialty_catalog_id_fk": {
          "name": "specialty_catalog_parent_id_specialty_catalog_id_fk",
          "tableFrom": "specialty_catalog",
          "tableTo": "specialty_catalog",
          "columnsFrom": ["parent_id"],
          "columnsTo": ["id"],
          "onDelete": "no action",
          "onUpdate": "no action"
        }
      },
      "compositePrimaryKeys": {},
      "uniqueConstraints": {},
      "policies": {},
      "checkConstraints": {},
      "isRLSEnabled": false
    },
    "public.supervision_requests": {
      "name": "supervision_requests",
      "schema": "",
      "columns": {
        "id": {
          "name": "id",
          "type": "uuid",
          "primaryKey": true,
          "notNull": true,
          "default": "gen_random_uuid()"
        },
        "supervisee_id": {
          "name": "supervisee_id",
          "type": "uuid",
          "primaryKey": false,
          "notNull": true
        },
        "supervisor_id": {
          "name": "supervisor_id",
          "type": "uuid",
          "primaryKey": false,
          "notNull": false
        },
        "service_product_id": {
          "name": "service_product_id",
          "type": "uuid",
          "primaryKey": false,
          "notNull": false
        },
        "status": {
          "name": "status",
          "type": "supervision_status",
          "typeSchema": "public",
          "primaryKey": false,
          "notNull": true,
          "default": "'draft'"
        },
        "retention_days": {
          "name": "retention_days",
          "type": "integer",
          "primaryKey": false,
          "notNull": true
        },
        "retention_expires_at": {
          "name": "retention_expires_at",
          "type": "timestamp with time zone",
          "primaryKey": false,
          "notNull": false
        },
        "urgency": {
          "name": "urgency",
          "type": "urgency",
          "typeSchema": "public",
          "primaryKey": false,
          "notNull": false
        },
        "desired_deadline": {
          "name": "desired_deadline",
          "type": "date",
          "primaryKey": false,
          "notNull": false
        },
        "created_at": {
          "name": "created_at",
          "type": "timestamp with time zone",
          "primaryKey": false,
          "notNull": true,
          "default": "now()"
        },
        "updated_at": {
          "name": "updated_at",
          "type": "timestamp with time zone",
          "primaryKey": false,
          "notNull": true,
          "default": "now()"
        }
      },
      "indexes": {
        "supervision_requests_supervisee_status_idx": {
          "name": "supervision_requests_supervisee_status_idx",
          "columns": [
            {
              "expression": "supervisee_id",
              "isExpression": false,
              "asc": true,
              "nulls": "last"
            },
            {
              "expression": "status",
              "isExpression": false,
              "asc": true,
              "nulls": "last"
            }
          ],
          "isUnique": false,
          "concurrently": false,
          "method": "btree",
          "with": {}
        },
        "supervision_requests_supervisor_status_idx": {
          "name": "supervision_requests_supervisor_status_idx",
          "columns": [
            {
              "expression": "supervisor_id",
              "isExpression": false,
              "asc": true,
              "nulls": "last"
            },
            {
              "expression": "status",
              "isExpression": false,
              "asc": true,
              "nulls": "last"
            }
          ],
          "isUnique": false,
          "concurrently": false,
          "method": "btree",
          "with": {}
        }
      },
      "foreignKeys": {
        "supervision_requests_supervisee_id_users_id_fk": {
          "name": "supervision_requests_supervisee_id_users_id_fk",
          "tableFrom": "supervision_requests",
          "tableTo": "users",
          "columnsFrom": ["supervisee_id"],
          "columnsTo": ["id"],
          "onDelete": "no action",
          "onUpdate": "no action"
        },
        "supervision_requests_supervisor_id_users_id_fk": {
          "name": "supervision_requests_supervisor_id_users_id_fk",
          "tableFrom": "supervision_requests",
          "tableTo": "users",
          "columnsFrom": ["supervisor_id"],
          "columnsTo": ["id"],
          "onDelete": "no action",
          "onUpdate": "no action"
        },
        "supervision_requests_service_product_id_service_products_id_fk": {
          "name": "supervision_requests_service_product_id_service_products_id_fk",
          "tableFrom": "supervision_requests",
          "tableTo": "service_products",
          "columnsFrom": ["service_product_id"],
          "columnsTo": ["id"],
          "onDelete": "no action",
          "onUpdate": "no action"
        }
      },
      "compositePrimaryKeys": {},
      "uniqueConstraints": {},
      "policies": {},
      "checkConstraints": {},
      "isRLSEnabled": false
    },
    "public.supervisor_profiles": {
      "name": "supervisor_profiles",
      "schema": "",
      "columns": {
        "id": {
          "name": "id",
          "type": "uuid",
          "primaryKey": true,
          "notNull": true,
          "default": "gen_random_uuid()"
        },
        "user_id": {
          "name": "user_id",
          "type": "uuid",
          "primaryKey": false,
          "notNull": true
        },
        "display_name": {
          "name": "display_name",
          "type": "text",
          "primaryKey": false,
          "notNull": true
        },
        "photo_url": {
          "name": "photo_url",
          "type": "text",
          "primaryKey": false,
          "notNull": false
        },
        "headline": {
          "name": "headline",
          "type": "text",
          "primaryKey": false,
          "notNull": false
        },
        "bio": {
          "name": "bio",
          "type": "text",
          "primaryKey": false,
          "notNull": false
        },
        "years_of_experience": {
          "name": "years_of_experience",
          "type": "integer",
          "primaryKey": false,
          "notNull": false
        },
        "signature_storage_key": {
          "name": "signature_storage_key",
          "type": "text",
          "primaryKey": false,
          "notNull": false
        },
        "verification_status": {
          "name": "verification_status",
          "type": "verification_status",
          "typeSchema": "public",
          "primaryKey": false,
          "notNull": true,
          "default": "'pending'"
        },
        "verified_at": {
          "name": "verified_at",
          "type": "timestamp with time zone",
          "primaryKey": false,
          "notNull": false
        },
        "visibility": {
          "name": "visibility",
          "type": "profile_visibility",
          "typeSchema": "public",
          "primaryKey": false,
          "notNull": true,
          "default": "'hidden'"
        },
        "avg_response_minutes": {
          "name": "avg_response_minutes",
          "type": "integer",
          "primaryKey": false,
          "notNull": false
        },
        "accept_rate": {
          "name": "accept_rate",
          "type": "numeric(4, 3)",
          "primaryKey": false,
          "notNull": false
        },
        "total_completed": {
          "name": "total_completed",
          "type": "integer",
          "primaryKey": false,
          "notNull": true,
          "default": 0
        },
        "average_rating": {
          "name": "average_rating",
          "type": "numeric(3, 2)",
          "primaryKey": false,
          "notNull": false
        },
        "created_at": {
          "name": "created_at",
          "type": "timestamp with time zone",
          "primaryKey": false,
          "notNull": true,
          "default": "now()"
        },
        "updated_at": {
          "name": "updated_at",
          "type": "timestamp with time zone",
          "primaryKey": false,
          "notNull": true,
          "default": "now()"
        }
      },
      "indexes": {
        "supervisor_profiles_user_id_unique": {
          "name": "supervisor_profiles_user_id_unique",
          "columns": [
            {
              "expression": "user_id",
              "isExpression": false,
              "asc": true,
              "nulls": "last"
            }
          ],
          "isUnique": true,
          "concurrently": false,
          "method": "btree",
          "with": {}
        },
        "supervisor_profiles_visibility_verification_idx": {
          "name": "supervisor_profiles_visibility_verification_idx",
          "columns": [
            {
              "expression": "visibility",
              "isExpression": false,
              "asc": true,
              "nulls": "last"
            },
            {
              "expression": "verification_status",
              "isExpression": false,
              "asc": true,
              "nulls": "last"
            }
          ],
          "isUnique": false,
          "concurrently": false,
          "method": "btree",
          "with": {}
        }
      },
      "foreignKeys": {
        "supervisor_profiles_user_id_users_id_fk": {
          "name": "supervisor_profiles_user_id_users_id_fk",
          "tableFrom": "supervisor_profiles",
          "tableTo": "users",
          "columnsFrom": ["user_id"],
          "columnsTo": ["id"],
          "onDelete": "no action",
          "onUpdate": "no action"
        }
      },
      "compositePrimaryKeys": {},
      "uniqueConstraints": {},
      "policies": {},
      "checkConstraints": {},
      "isRLSEnabled": false
    },
    "public.supervisor_specialties": {
      "name": "supervisor_specialties",
      "schema": "",
      "columns": {
        "supervisor_profile_id": {
          "name": "supervisor_profile_id",
          "type": "uuid",
          "primaryKey": false,
          "notNull": true
        },
        "specialty_id": {
          "name": "specialty_id",
          "type": "uuid",
          "primaryKey": false,
          "notNull": true
        }
      },
      "indexes": {
        "supervisor_specialties_specialty_id_idx": {
          "name": "supervisor_specialties_specialty_id_idx",
          "columns": [
            {
              "expression": "specialty_id",
              "isExpression": false,
              "asc": true,
              "nulls": "last"
            }
          ],
          "isUnique": false,
          "concurrently": false,
          "method": "btree",
          "with": {}
        }
      },
      "foreignKeys": {
        "supervisor_specialties_supervisor_profile_id_supervisor_profiles_id_fk": {
          "name": "supervisor_specialties_supervisor_profile_id_supervisor_profiles_id_fk",
          "tableFrom": "supervisor_specialties",
          "tableTo": "supervisor_profiles",
          "columnsFrom": ["supervisor_profile_id"],
          "columnsTo": ["id"],
          "onDelete": "no action",
          "onUpdate": "no action"
        },
        "supervisor_specialties_specialty_id_specialty_catalog_id_fk": {
          "name": "supervisor_specialties_specialty_id_specialty_catalog_id_fk",
          "tableFrom": "supervisor_specialties",
          "tableTo": "specialty_catalog",
          "columnsFrom": ["specialty_id"],
          "columnsTo": ["id"],
          "onDelete": "no action",
          "onUpdate": "no action"
        }
      },
      "compositePrimaryKeys": {
        "supervisor_specialties_supervisor_profile_id_specialty_id_pk": {
          "name": "supervisor_specialties_supervisor_profile_id_specialty_id_pk",
          "columns": ["supervisor_profile_id", "specialty_id"]
        }
      },
      "uniqueConstraints": {},
      "policies": {},
      "checkConstraints": {},
      "isRLSEnabled": false
    },
    "public.terms_versions": {
      "name": "terms_versions",
      "schema": "",
      "columns": {
        "id": {
          "name": "id",
          "type": "uuid",
          "primaryKey": true,
          "notNull": true,
          "default": "gen_random_uuid()"
        },
        "kind": {
          "name": "kind",
          "type": "terms_kind",
          "typeSchema": "public",
          "primaryKey": false,
          "notNull": true
        },
        "version": {
          "name": "version",
          "type": "text",
          "primaryKey": false,
          "notNull": true
        },
        "content_md": {
          "name": "content_md",
          "type": "text",
          "primaryKey": false,
          "notNull": false
        },
        "effective_from": {
          "name": "effective_from",
          "type": "date",
          "primaryKey": false,
          "notNull": false
        },
        "is_active": {
          "name": "is_active",
          "type": "boolean",
          "primaryKey": false,
          "notNull": true,
          "default": true
        }
      },
      "indexes": {},
      "foreignKeys": {},
      "compositePrimaryKeys": {},
      "uniqueConstraints": {},
      "policies": {},
      "checkConstraints": {},
      "isRLSEnabled": false
    },
    "public.users": {
      "name": "users",
      "schema": "",
      "columns": {
        "id": {
          "name": "id",
          "type": "uuid",
          "primaryKey": true,
          "notNull": true,
          "default": "gen_random_uuid()"
        },
        "email": {
          "name": "email",
          "type": "text",
          "primaryKey": false,
          "notNull": true
        },
        "password_hash": {
          "name": "password_hash",
          "type": "text",
          "primaryKey": false,
          "notNull": false
        },
        "role": {
          "name": "role",
          "type": "user_role",
          "typeSchema": "public",
          "primaryKey": false,
          "notNull": true
        },
        "display_name_enc": {
          "name": "display_name_enc",
          "type": "bytea",
          "primaryKey": false,
          "notNull": false
        },
        "phone_enc": {
          "name": "phone_enc",
          "type": "bytea",
          "primaryKey": false,
          "notNull": false
        },
        "totp_secret_enc": {
          "name": "totp_secret_enc",
          "type": "bytea",
          "primaryKey": false,
          "notNull": false
        },
        "totp_enabled": {
          "name": "totp_enabled",
          "type": "boolean",
          "primaryKey": false,
          "notNull": true,
          "default": false
        },
        "email_verified_at": {
          "name": "email_verified_at",
          "type": "timestamp with time zone",
          "primaryKey": false,
          "notNull": false
        },
        "last_login_at": {
          "name": "last_login_at",
          "type": "timestamp with time zone",
          "primaryKey": false,
          "notNull": false
        },
        "failed_login_count": {
          "name": "failed_login_count",
          "type": "integer",
          "primaryKey": false,
          "notNull": true,
          "default": 0
        },
        "locked_until": {
          "name": "locked_until",
          "type": "timestamp with time zone",
          "primaryKey": false,
          "notNull": false
        },
        "status": {
          "name": "status",
          "type": "user_status",
          "typeSchema": "public",
          "primaryKey": false,
          "notNull": true,
          "default": "'active'"
        },
        "organization_id": {
          "name": "organization_id",
          "type": "uuid",
          "primaryKey": false,
          "notNull": false
        },
        "created_at": {
          "name": "created_at",
          "type": "timestamp with time zone",
          "primaryKey": false,
          "notNull": true,
          "default": "now()"
        },
        "updated_at": {
          "name": "updated_at",
          "type": "timestamp with time zone",
          "primaryKey": false,
          "notNull": true,
          "default": "now()"
        },
        "deleted_at": {
          "name": "deleted_at",
          "type": "timestamp with time zone",
          "primaryKey": false,
          "notNull": false
        }
      },
      "indexes": {
        "users_email_unique": {
          "name": "users_email_unique",
          "columns": [
            {
              "expression": "email",
              "isExpression": false,
              "asc": true,
              "nulls": "last"
            }
          ],
          "isUnique": true,
          "concurrently": false,
          "method": "btree",
          "with": {}
        },
        "users_role_status_idx": {
          "name": "users_role_status_idx",
          "columns": [
            {
              "expression": "role",
              "isExpression": false,
              "asc": true,
              "nulls": "last"
            },
            {
              "expression": "status",
              "isExpression": false,
              "asc": true,
              "nulls": "last"
            }
          ],
          "isUnique": false,
          "concurrently": false,
          "method": "btree",
          "with": {}
        }
      },
      "foreignKeys": {},
      "compositePrimaryKeys": {},
      "uniqueConstraints": {},
      "policies": {},
      "checkConstraints": {},
      "isRLSEnabled": false
    }
  },
  "enums": {
    "public.booking_status": {
      "name": "booking_status",
      "schema": "public",
      "values": [
        "scheduled",
        "rescheduled",
        "cancelled",
        "completed",
        "no_show_supervisee",
        "no_show_supervisor"
      ]
    },
    "public.case_file_kind": {
      "name": "case_file_kind",
      "schema": "public",
      "values": [
        "report_draft",
        "test_result",
        "scoring_sheet",
        "response_sheet",
        "behavioral_observation",
        "interview_summary",
        "other",
        "direct_edit_revision"
      ]
    },
    "public.comment_severity": {
      "name": "comment_severity",
      "schema": "public",
      "values": ["info", "suggestion", "warning", "critical"]
    },
    "public.consent_type": {
      "name": "consent_type",
      "schema": "public",
      "values": ["tos", "privacy", "sensitive", "marketing"]
    },
    "public.deletion_status": {
      "name": "deletion_status",
      "schema": "public",
      "values": ["pending", "approved", "rejected", "completed"]
    },
    "public.deletion_target_type": {
      "name": "deletion_target_type",
      "schema": "public",
      "values": ["user", "case_file", "case_packet", "supervision_request"]
    },
    "public.dispute_status": {
      "name": "dispute_status",
      "schema": "public",
      "values": [
        "open",
        "investigating",
        "resolved_refund",
        "resolved_partial",
        "resolved_denied",
        "closed"
      ]
    },
    "public.file_access_action": {
      "name": "file_access_action",
      "schema": "public",
      "values": ["view", "download", "upload", "delete"]
    },
    "public.payment_status": {
      "name": "payment_status",
      "schema": "public",
      "values": [
        "pending",
        "paid",
        "failed",
        "partially_refunded",
        "refunded",
        "cancelled"
      ]
    },
    "public.payout_status": {
      "name": "payout_status",
      "schema": "public",
      "values": ["scheduled", "held", "paid", "failed"]
    },
    "public.phi_scan_status": {
      "name": "phi_scan_status",
      "schema": "public",
      "values": ["pending", "clean", "suspicious"]
    },
    "public.preferred_method": {
      "name": "preferred_method",
      "schema": "public",
      "values": ["async_comment", "direct_edit", "zoom", "comment_plus_zoom"]
    },
    "public.profile_visibility": {
      "name": "profile_visibility",
      "schema": "public",
      "values": ["hidden", "public", "private"]
    },
    "public.qualification_status": {
      "name": "qualification_status",
      "schema": "public",
      "values": ["pending", "approved", "rejected"]
    },
    "public.refund_status": {
      "name": "refund_status",
      "schema": "public",
      "values": ["requested", "approved", "rejected", "completed"]
    },
    "public.report_status": {
      "name": "report_status",
      "schema": "public",
      "values": ["open", "reviewing", "resolved", "dismissed"]
    },
    "public.review_status": {
      "name": "review_status",
      "schema": "public",
      "values": ["visible", "hidden", "reported"]
    },
    "public.service_product_kind": {
      "name": "service_product_kind",
      "schema": "public",
      "values": [
        "async_comment",
        "async_direct_edit",
        "zoom_60",
        "zoom_90",
        "urgent_24h"
      ]
    },
    "public.supervision_status": {
      "name": "supervision_status",
      "schema": "public",
      "values": [
        "draft",
        "submitted",
        "awaiting_payment",
        "paid",
        "awaiting_supervisor_review",
        "accepted",
        "rejected",
        "additional_info_requested",
        "in_review",
        "feedback_submitted",
        "meeting_scheduled",
        "meeting_completed",
        "completion_record_issued",
        "completed",
        "cancelled",
        "refunded",
        "expired",
        "deleted"
      ]
    },
    "public.terms_kind": {
      "name": "terms_kind",
      "schema": "public",
      "values": ["tos", "privacy", "sensitive", "marketing"]
    },
    "public.urgency": {
      "name": "urgency",
      "schema": "public",
      "values": ["normal", "urgent_24h"]
    },
    "public.user_role": {
      "name": "user_role",
      "schema": "public",
      "values": ["supervisee", "supervisor", "admin"]
    },
    "public.user_status": {
      "name": "user_status",
      "schema": "public",
      "values": ["active", "suspended", "withdrawn"]
    },
    "public.verification_status": {
      "name": "verification_status",
      "schema": "public",
      "values": ["pending", "approved", "rejected", "revoked"]
    },
    "public.virus_scan_status": {
      "name": "virus_scan_status",
      "schema": "public",
      "values": ["pending", "clean", "infected", "error"]
    }
  },
  "schemas": {},
  "sequences": {},
  "roles": {},
  "policies": {},
  "views": {},
  "_meta": {
    "columns": {},
    "schemas": {},
    "tables": {}
  }
}
